{
    "settings": {
      "iconSize": 50,
      "foldThick": 15,
      "iconHoverBrighter": 0.2,
      "iconPressDarker": -0.2
    },
    "docks": {
        "top": [
            {
                "name": "Content",
                "icon": "D:/SOUL/Icons/Content.bmp",
                "target": "D:/CONTENT"
            }
        ],
        "right": [
            {
                "name": "Warcraft III",
                "target": "C:/Programs/Games/Warcraft III/Warcraft III.exe"
            },
            {
                "name": "cmd",
                "icon": "D:/SOUL/Icons/cmd.png",
                "target": "D:/SOUL/Programs/Links/Dev/cmd.lnk"
            },
            {
                "name": "Projects",
                "icon": "D:/SOUL/Icons/Projects2.bmp",
                "target": "D:/DEV/1__Projects"
            },
            {
                "name": "Gmail",
                "icon": "D:/SOUL/Icons/gmail.png",
                "target": "https://mail.google.com/mail/u/0/#inbox"
            }
        ],
        "bottom": [],
        "left": []
    }
}
